file_trigger/__init__.py
file_trigger/__main__.py
file_trigger/notify.py
file_trigger/adapter/__init__.py
file_trigger/adapter/config_file.py
file_trigger/adapter/event_handler.py
file_trigger/adapter/executor.py
file_trigger/adapter/filesys.py
file_trigger/adapter/handler.py
file_trigger/adapter/subprocess_.py
file_trigger/adapter/collector/__init__.py
file_trigger/adapter/collector/file_info.py
file_trigger/command/__init__.py
file_trigger/command/common.py
file_trigger/command/push.py
file_trigger/command/watch.py
file_trigger/model/__init__.py
file_trigger/model/collector.py
file_trigger/model/command.py
file_trigger/model/config.py
file_trigger/model/exceptions.py
file_trigger/scripts/__init__.py
file_trigger/scripts/build_windows_service.py
file_trigger/scripts/util/__init__.py
file_trigger/scripts/util/prompt_toolkit.py
file_trigger/util/__init__.py
file_trigger/util/bool_.py
file_trigger/util/dataclasses_.py
file_trigger/util/datetime_.py
file_trigger/util/dict_.py
file_trigger/util/importlib_.py
file_trigger/util/re_.py
file_trigger/util/watchdog.py
file_trigger/util/logging_/__init__.py
file_trigger/util/logging_/handlers.py
file_trigger/util/watchdog/__init__.py
file_trigger/util/watchdog/observers/__init__.py
file_trigger-0.11.dist-info/METADATA
file_trigger-0.11.dist-info/WHEEL
file_trigger-0.11.dist-info/entry_points.txt
file_trigger-0.11.dist-info/top_level.txt
file_trigger-0.11.dist-info/RECORD
