Metadata-Version: 2.1
Name: file-trigger
Version: 0.11
Summary: Simple file trigger based on rules
Author: Eric Gjertsen
Author-email: ericgj72@gmail.com
License: MIT
Classifier: Programming Language :: Python :: 3
Classifier: Operating System :: OS Independent
Classifier: Development Status :: 2 - Pre-Alpha
Classifier: License :: OSI Approved :: MIT License
Requires-Dist: tomli
Requires-Dist: guilogger
Requires-Dist: watchdog (<2.2.0,>=2.1.9)
Provides-Extra: service-install
Requires-Dist: chevron ; extra == 'service-install'
Requires-Dist: prompt-toolkit ; extra == 'service-install'
Provides-Extra: test
Requires-Dist: webob ; extra == 'test'
Requires-Dist: pytest ; extra == 'test'
Requires-Dist: pytest-random-order ; extra == 'test'
Requires-Dist: hypothesis ; extra == 'test'
